requests_reviewer-0.1.3.dist-info/metadata.json
requests_reviewer-0.1.3.dist-info/WHEEL
requests_reviewer-0.1.3.dist-info/top_level.txt
requests_reviewer-0.1.3.dist-info/DESCRIPTION.rst
requests_reviewer-0.1.3.dist-info/METADATA
requests_reviewer-0.1.3.dist-info/RECORD
requests_reviewer/requests_reviewer.py
requests_reviewer/rules.py
requests_reviewer/__init__.py
requests_reviewer/rules_helpers.py
