Metadata-Version: 2.0
Name: requests-reviewer
Version: 0.1.3
Summary: Take a HTTP response from requests and adjust the return code based on ISP suspension messages, CDN overload messages and similar
Home-page: https://github.com/chorsley/requests_reviewer
Author: Chris Horsley
Author-email: chris.horsley@csirtfoundry.com
License: ISCL
Keywords: requests_reviewer
Platform: UNKNOWN
Classifier: Development Status :: 2 - Pre-Alpha
Classifier: Intended Audience :: Developers
Classifier: License :: OSI Approved :: ISC License (ISCL)
Classifier: Natural Language :: English
Classifier: Programming Language :: Python :: 2
Classifier: Programming Language :: Python :: 2.6
Classifier: Programming Language :: Python :: 2.7
Classifier: Programming Language :: Python :: 3
Classifier: Programming Language :: Python :: 3.3
Classifier: Programming Language :: Python :: 3.4
Classifier: Programming Language :: Python :: 3.5
Requires-Dist: requests (==2.9.1)
